{
  "project_info": {
    "project_number": "701813741605",
    "firebase_url": "https://myfindfood-5ac46.firebaseio.com",
    "project_id": "myfindfood-5ac46",
    "storage_bucket": "myfindfood-5ac46.appspot.com"
  },
  "client": [
    {
      "client_info": {
        "mobilesdk_app_id": "1:701813741605:android:c9135bf4b131515b",
        "android_client_info": {
          "package_name": "com.anhtu.hongngoc.findfood"
        }
      },
      "oauth_client": [
        {
          "client_id": "701813741605-ae75pmseno21ol4g322ipdam1t5etmeb.apps.googleusercontent.com",
          "client_type": 3
        }
      ],
      "api_key": [
        {
          "current_key": "AIzaSyDLe38WB436NpCG_N2LjkfeUBXkjlzvGHI"
        }
      ],
      "services": {
        "analytics_service": {
          "status": 1
        },
        "appinvite_service": {
          "status": 1,
          "other_platform_oauth_client": []
        },
        "ads_service": {
          "status": 2
        }
      }
    }
  ],
  "configuration_version": "1"
}